<?xml version='1.0' encoding='utf-8'?>
<!-- OPTIMIZADO POR The Spring -->
<TextureAtlas imagePath="noteComboNumbers">
    <SubTexture name="0 light0000" x="0" y="0" width="148" height="201" frameWidth="164" frameHeight="217" frameX="-10" frameY="-3"/>
    <SubTexture name="0 light0001" x="149" y="0" width="135" height="188" frameWidth="164" frameHeight="217" frameX="-16" frameY="-9"/>
    <SubTexture name="0 light0002" x="285" y="0" width="129" height="176" frameWidth="164" frameHeight="217" frameX="-16" frameY="-16"/>
    <SubTexture name="0 light0003" x="415" y="0" width="130" height="178" frameWidth="164" frameHeight="217" frameX="-16" frameY="-15"/>
    <SubTexture name="0 light0004" x="546" y="0" width="132" height="181" frameWidth="164" frameHeight="217" frameX="-16" frameY="-13"/>
    <SubTexture name="0 light0005" x="679" y="0" width="133" height="183" frameWidth="164" frameHeight="217" frameX="-16" frameY="-12"/>
    <SubTexture name="0 light0006" x="813" y="0" width="134" height="187" frameWidth="164" frameHeight="217" frameX="-16" frameY="-10"/>
    <SubTexture name="0 light0007" x="948" y="0" width="136" height="189" frameWidth="164" frameHeight="217" frameX="-16" frameY="-9"/>
    <SubTexture name="0 light0008" x="1085" y="0" width="138" height="191" frameWidth="164" frameHeight="217" frameX="-15" frameY="-8"/>
    <SubTexture name="0 light0009" x="1224" y="0" width="140" height="194" frameWidth="164" frameHeight="217" frameX="-14" frameY="-6"/>
    <SubTexture name="0 light0010" x="1365" y="0" width="141" height="194" frameWidth="164" frameHeight="217" frameX="-13" frameY="-6"/>
    <SubTexture name="0 light0011" x="1507" y="0" width="129" height="176" frameWidth="164" frameHeight="217" frameX="-16" frameY="-16"/>
    <SubTexture name="0 light0012" x="1507" y="0" width="129" height="176" frameWidth="164" frameHeight="217" frameX="-16" frameY="-16"/>
    <SubTexture name="0 light0013" x="1507" y="0" width="129" height="176" frameWidth="164" frameHeight="217" frameX="-16" frameY="-16"/>
    <SubTexture name="0 light0014" x="1507" y="0" width="129" height="176" frameWidth="164" frameHeight="217" frameX="-16" frameY="-16"/>
    <SubTexture name="0 light0015" x="1507" y="0" width="129" height="176" frameWidth="164" frameHeight="217" frameX="-16" frameY="-16"/>
    <SubTexture name="1 light0000" x="1637" y="0" width="123" height="195" frameWidth="134" frameHeight="201" frameX="-7" frameY="0"/>
    <SubTexture name="1 light0001" x="1761" y="0" width="111" height="182" frameWidth="134" frameHeight="201" frameX="-13" frameY="-7"/>
    <SubTexture name="1 light0002" x="0" y="211" width="101" height="170" frameWidth="134" frameHeight="201" frameX="-16" frameY="-13"/>
    <SubTexture name="1 light0003" x="102" y="211" width="102" height="172" frameWidth="134" frameHeight="201" frameX="-16" frameY="-12"/>
    <SubTexture name="1 light0004" x="205" y="211" width="104" height="175" frameWidth="134" frameHeight="201" frameX="-16" frameY="-11"/>
    <SubTexture name="1 light0005" x="310" y="211" width="106" height="178" frameWidth="134" frameHeight="201" frameX="-15" frameY="-9"/>
    <SubTexture name="1 light0006" x="417" y="211" width="109" height="180" frameWidth="134" frameHeight="201" frameX="-14" frameY="-8"/>
    <SubTexture name="1 light0007" x="527" y="211" width="111" height="184" frameWidth="134" frameHeight="201" frameX="-13" frameY="-6"/>
    <SubTexture name="1 light0008" x="639" y="211" width="113" height="186" frameWidth="134" frameHeight="201" frameX="-12" frameY="-5"/>
    <SubTexture name="1 light0009" x="753" y="211" width="115" height="188" frameWidth="134" frameHeight="201" frameX="-11" frameY="-4"/>
    <SubTexture name="1 light0010" x="869" y="211" width="116" height="188" frameWidth="134" frameHeight="201" frameX="-10" frameY="-4"/>
    <SubTexture name="1 light0011" x="986" y="211" width="101" height="170" frameWidth="134" frameHeight="201" frameX="-16" frameY="-13"/>
    <SubTexture name="1 light0012" x="1088" y="211" width="101" height="169" frameWidth="134" frameHeight="201" frameX="-16" frameY="-14"/>
    <SubTexture name="1 light0013" x="1190" y="211" width="101" height="169" frameWidth="134" frameHeight="201" frameX="-16" frameY="-14"/>
    <SubTexture name="1 light0014" x="1088" y="211" width="101" height="169" frameWidth="134" frameHeight="201" frameX="-16" frameY="-14"/>
    <SubTexture name="1 light0015" x="1190" y="211" width="101" height="169" frameWidth="134" frameHeight="201" frameX="-16" frameY="-14"/>
    <SubTexture name="2 light0000" x="1292" y="211" width="148" height="204" frameWidth="157" frameHeight="218" frameX="-5" frameY="-3"/>
    <SubTexture name="2 light0001" x="1441" y="211" width="135" height="192" frameWidth="157" frameHeight="218" frameX="-11" frameY="-9"/>
    <SubTexture name="2 light0002" x="1577" y="211" width="125" height="179" frameWidth="157" frameHeight="218" frameX="-16" frameY="-15"/>
    <SubTexture name="2 light0003" x="1703" y="211" width="126" height="181" frameWidth="157" frameHeight="218" frameX="-16" frameY="-14"/>
    <SubTexture name="2 light0004" x="0" y="425" width="129" height="185" frameWidth="157" frameHeight="218" frameX="-14" frameY="-12"/>
    <SubTexture name="2 light0005" x="130" y="425" width="131" height="187" frameWidth="157" frameHeight="218" frameX="-13" frameY="-11"/>
    <SubTexture name="2 light0006" x="262" y="425" width="134" height="190" frameWidth="157" frameHeight="218" frameX="-12" frameY="-10"/>
    <SubTexture name="2 light0007" x="397" y="425" width="136" height="192" frameWidth="157" frameHeight="218" frameX="-11" frameY="-9"/>
    <SubTexture name="2 light0008" x="534" y="425" width="139" height="194" frameWidth="157" frameHeight="218" frameX="-9" frameY="-8"/>
    <SubTexture name="2 light0009" x="674" y="425" width="141" height="196" frameWidth="157" frameHeight="218" frameX="-8" frameY="-7"/>
    <SubTexture name="2 light0010" x="816" y="425" width="142" height="197" frameWidth="157" frameHeight="218" frameX="-8" frameY="-6"/>
    <SubTexture name="2 light0011" x="959" y="425" width="124" height="178" frameWidth="157" frameHeight="218" frameX="-16" frameY="-16"/>
    <SubTexture name="2 light0012" x="959" y="425" width="124" height="178" frameWidth="157" frameHeight="218" frameX="-16" frameY="-16"/>
    <SubTexture name="2 light0013" x="959" y="425" width="124" height="178" frameWidth="157" frameHeight="218" frameX="-16" frameY="-16"/>
    <SubTexture name="2 light0014" x="959" y="425" width="124" height="178" frameWidth="157" frameHeight="218" frameX="-16" frameY="-16"/>
    <SubTexture name="2 light0015" x="1084" y="425" width="124" height="178" frameWidth="157" frameHeight="218" frameX="-16" frameY="-16"/>
    <SubTexture name="3 light0000" x="1209" y="425" width="148" height="205" frameWidth="158" frameHeight="211" frameX="-5" frameY="-1"/>
    <SubTexture name="3 light0001" x="1358" y="425" width="136" height="193" frameWidth="158" frameHeight="211" frameX="-11" frameY="-7"/>
    <SubTexture name="3 light0002" x="1495" y="425" width="125" height="180" frameWidth="158" frameHeight="211" frameX="-16" frameY="-14"/>
    <SubTexture name="3 light0003" x="1621" y="425" width="126" height="183" frameWidth="158" frameHeight="211" frameX="-16" frameY="-12"/>
    <SubTexture name="3 light0004" x="1748" y="425" width="130" height="186" frameWidth="158" frameHeight="211" frameX="-14" frameY="-11"/>
    <SubTexture name="3 light0005" x="0" y="640" width="132" height="189" frameWidth="158" frameHeight="211" frameX="-13" frameY="-9"/>
    <SubTexture name="3 light0006" x="133" y="640" width="135" height="192" frameWidth="158" frameHeight="211" frameX="-12" frameY="-8"/>
    <SubTexture name="3 light0007" x="269" y="640" width="138" height="194" frameWidth="158" frameHeight="211" frameX="-10" frameY="-7"/>
    <SubTexture name="3 light0008" x="408" y="640" width="140" height="196" frameWidth="158" frameHeight="211" frameX="-9" frameY="-6"/>
    <SubTexture name="3 light0009" x="549" y="640" width="142" height="199" frameWidth="158" frameHeight="211" frameX="-8" frameY="-4"/>
    <SubTexture name="3 light0010" x="692" y="640" width="143" height="199" frameWidth="158" frameHeight="211" frameX="-8" frameY="-4"/>
    <SubTexture name="3 light0011" x="836" y="640" width="125" height="180" frameWidth="158" frameHeight="211" frameX="-16" frameY="-14"/>
    <SubTexture name="3 light0012" x="962" y="640" width="125" height="180" frameWidth="158" frameHeight="211" frameX="-16" frameY="-14"/>
    <SubTexture name="3 light0013" x="962" y="640" width="125" height="180" frameWidth="158" frameHeight="211" frameX="-16" frameY="-14"/>
    <SubTexture name="3 light0014" x="962" y="640" width="125" height="180" frameWidth="158" frameHeight="211" frameX="-16" frameY="-14"/>
    <SubTexture name="3 light0015" x="1088" y="640" width="125" height="180" frameWidth="158" frameHeight="211" frameX="-16" frameY="-14"/>
    <SubTexture name="4 light0000" x="1214" y="640" width="136" height="189" frameWidth="149" frameHeight="206" frameX="-5" frameY="-6"/>
    <SubTexture name="4 light0001" x="1351" y="640" width="124" height="177" frameWidth="149" frameHeight="206" frameX="-11" frameY="-12"/>
    <SubTexture name="4 light0002" x="1476" y="640" width="113" height="165" frameWidth="149" frameHeight="206" frameX="-16" frameY="-18"/>
    <SubTexture name="4 light0003" x="1590" y="640" width="114" height="167" frameWidth="149" frameHeight="206" frameX="-16" frameY="-17"/>
    <SubTexture name="4 light0004" x="1705" y="640" width="118" height="170" frameWidth="149" frameHeight="206" frameX="-14" frameY="-16"/>
    <SubTexture name="4 light0005" x="0" y="849" width="120" height="173" frameWidth="149" frameHeight="206" frameX="-13" frameY="-14"/>
    <SubTexture name="4 light0006" x="121" y="849" width="122" height="175" frameWidth="149" frameHeight="206" frameX="-12" frameY="-13"/>
    <SubTexture name="4 light0007" x="244" y="849" width="124" height="178" frameWidth="149" frameHeight="206" frameX="-11" frameY="-12"/>
    <SubTexture name="4 light0008" x="369" y="849" width="127" height="180" frameWidth="149" frameHeight="206" frameX="-9" frameY="-11"/>
    <SubTexture name="4 light0009" x="497" y="849" width="129" height="182" frameWidth="149" frameHeight="206" frameX="-8" frameY="-10"/>
    <SubTexture name="4 light0010" x="627" y="849" width="130" height="183" frameWidth="149" frameHeight="206" frameX="-8" frameY="-9"/>
    <SubTexture name="4 light0011" x="758" y="849" width="112" height="165" frameWidth="149" frameHeight="206" frameX="-16" frameY="-18"/>
    <SubTexture name="4 light0012" x="758" y="849" width="112" height="165" frameWidth="149" frameHeight="206" frameX="-16" frameY="-18"/>
    <SubTexture name="4 light0013" x="758" y="849" width="112" height="165" frameWidth="149" frameHeight="206" frameX="-16" frameY="-18"/>
    <SubTexture name="4 light0014" x="758" y="849" width="112" height="165" frameWidth="149" frameHeight="206" frameX="-16" frameY="-18"/>
    <SubTexture name="4 light0015" x="758" y="849" width="112" height="165" frameWidth="149" frameHeight="206" frameX="-16" frameY="-18"/>
    <SubTexture name="5 light0000" x="871" y="849" width="148" height="199" frameWidth="164" frameHeight="213" frameX="-11" frameY="-1"/>
    <SubTexture name="5 light0001" x="1020" y="849" width="138" height="185" frameWidth="164" frameHeight="213" frameX="-15" frameY="-8"/>
    <SubTexture name="5 light0002" x="1159" y="849" width="130" height="174" frameWidth="164" frameHeight="213" frameX="-16" frameY="-14"/>
    <SubTexture name="5 light0003" x="1290" y="849" width="132" height="175" frameWidth="164" frameHeight="213" frameX="-16" frameY="-13"/>
    <SubTexture name="5 light0004" x="1423" y="849" width="133" height="179" frameWidth="164" frameHeight="213" frameX="-16" frameY="-11"/>
    <SubTexture name="5 light0005" x="1557" y="849" width="134" height="181" frameWidth="164" frameHeight="213" frameX="-16" frameY="-10"/>
    <SubTexture name="5 light0006" x="1692" y="849" width="136" height="185" frameWidth="164" frameHeight="213" frameX="-16" frameY="-8"/>
    <SubTexture name="5 light0007" x="0" y="1058" width="137" height="187" frameWidth="164" frameHeight="213" frameX="-16" frameY="-7"/>
    <SubTexture name="5 light0008" x="138" y="1058" width="138" height="189" frameWidth="164" frameHeight="213" frameX="-16" frameY="-6"/>
    <SubTexture name="5 light0009" x="277" y="1058" width="139" height="191" frameWidth="164" frameHeight="213" frameX="-16" frameY="-5"/>
    <SubTexture name="5 light0010" x="417" y="1058" width="140" height="191" frameWidth="164" frameHeight="213" frameX="-16" frameY="-5"/>
    <SubTexture name="5 light0011" x="558" y="1058" width="130" height="174" frameWidth="164" frameHeight="213" frameX="-16" frameY="-14"/>
    <SubTexture name="5 light0012" x="558" y="1058" width="130" height="174" frameWidth="164" frameHeight="213" frameX="-16" frameY="-14"/>
    <SubTexture name="5 light0013" x="558" y="1058" width="130" height="174" frameWidth="164" frameHeight="213" frameX="-16" frameY="-14"/>
    <SubTexture name="5 light0014" x="558" y="1058" width="130" height="174" frameWidth="164" frameHeight="213" frameX="-16" frameY="-14"/>
    <SubTexture name="5 light0015" x="689" y="1058" width="130" height="174" frameWidth="164" frameHeight="213" frameX="-16" frameY="-14"/>
    <SubTexture name="6 light0000" x="820" y="1058" width="146" height="203" frameWidth="162" frameHeight="222" frameX="-5" frameY="-7"/>
    <SubTexture name="6 light0001" x="967" y="1058" width="134" height="190" frameWidth="162" frameHeight="222" frameX="-11" frameY="-13"/>
    <SubTexture name="6 light0002" x="1102" y="1058" width="123" height="180" frameWidth="162" frameHeight="222" frameX="-16" frameY="-18"/>
    <SubTexture name="6 light0003" x="1226" y="1058" width="125" height="181" frameWidth="162" frameHeight="222" frameX="-15" frameY="-18"/>
    <SubTexture name="6 light0004" x="1352" y="1058" width="128" height="184" frameWidth="162" frameHeight="222" frameX="-14" frameY="-16"/>
    <SubTexture name="6 light0005" x="1481" y="1058" width="130" height="186" frameWidth="162" frameHeight="222" frameX="-13" frameY="-15"/>
    <SubTexture name="6 light0006" x="1612" y="1058" width="132" height="189" frameWidth="162" frameHeight="222" frameX="-12" frameY="-14"/>
    <SubTexture name="6 light0007" x="1745" y="1058" width="136" height="192" frameWidth="162" frameHeight="222" frameX="-10" frameY="-12"/>
    <SubTexture name="6 light0008" x="0" y="1271" width="138" height="194" frameWidth="162" frameHeight="222" frameX="-9" frameY="-11"/>
    <SubTexture name="6 light0009" x="139" y="1271" width="140" height="196" frameWidth="162" frameHeight="222" frameX="-8" frameY="-10"/>
    <SubTexture name="6 light0010" x="280" y="1271" width="140" height="196" frameWidth="162" frameHeight="222" frameX="-8" frameY="-10"/>
    <SubTexture name="6 light0011" x="421" y="1271" width="123" height="179" frameWidth="162" frameHeight="222" frameX="-16" frameY="-18"/>
    <SubTexture name="6 light0012" x="421" y="1271" width="123" height="179" frameWidth="162" frameHeight="222" frameX="-16" frameY="-18"/>
    <SubTexture name="6 light0013" x="421" y="1271" width="123" height="179" frameWidth="162" frameHeight="222" frameX="-16" frameY="-18"/>
    <SubTexture name="6 light0014" x="421" y="1271" width="123" height="179" frameWidth="162" frameHeight="222" frameX="-16" frameY="-18"/>
    <SubTexture name="6 light0015" x="421" y="1271" width="123" height="179" frameWidth="162" frameHeight="222" frameX="-16" frameY="-18"/>
    <SubTexture name="7 light0000" x="545" y="1271" width="134" height="198" frameWidth="149" frameHeight="205" frameX="-10" frameY="-1"/>
    <SubTexture name="7 light0001" x="680" y="1271" width="122" height="186" frameWidth="149" frameHeight="205" frameX="-16" frameY="-7"/>
    <SubTexture name="7 light0002" x="803" y="1271" width="115" height="172" frameWidth="149" frameHeight="205" frameX="-17" frameY="-14"/>
    <SubTexture name="7 light0003" x="919" y="1271" width="116" height="175" frameWidth="149" frameHeight="205" frameX="-17" frameY="-13"/>
    <SubTexture name="7 light0004" x="1036" y="1271" width="118" height="178" frameWidth="149" frameHeight="205" frameX="-17" frameY="-11"/>
    <SubTexture name="7 light0005" x="1155" y="1271" width="119" height="181" frameWidth="149" frameHeight="205" frameX="-17" frameY="-10"/>
    <SubTexture name="7 light0006" x="1275" y="1271" width="121" height="184" frameWidth="149" frameHeight="205" frameX="-16" frameY="-8"/>
    <SubTexture name="7 light0007" x="1397" y="1271" width="124" height="186" frameWidth="149" frameHeight="205" frameX="-15" frameY="-7"/>
    <SubTexture name="7 light0008" x="1522" y="1271" width="126" height="188" frameWidth="149" frameHeight="205" frameX="-14" frameY="-6"/>
    <SubTexture name="7 light0009" x="1649" y="1271" width="128" height="191" frameWidth="149" frameHeight="205" frameX="-13" frameY="-5"/>
    <SubTexture name="7 light0010" x="0" y="1479" width="129" height="192" frameWidth="149" frameHeight="205" frameX="-13" frameY="-4"/>
    <SubTexture name="7 light0011" x="130" y="1479" width="115" height="172" frameWidth="149" frameHeight="205" frameX="-17" frameY="-14"/>
    <SubTexture name="7 light0012" x="130" y="1479" width="115" height="172" frameWidth="149" frameHeight="205" frameX="-17" frameY="-14"/>
    <SubTexture name="7 light0013" x="130" y="1479" width="115" height="172" frameWidth="149" frameHeight="205" frameX="-17" frameY="-14"/>
    <SubTexture name="7 light0014" x="130" y="1479" width="115" height="172" frameWidth="149" frameHeight="205" frameX="-17" frameY="-14"/>
    <SubTexture name="7 light0015" x="246" y="1479" width="115" height="172" frameWidth="149" frameHeight="205" frameX="-17" frameY="-14"/>
    <SubTexture name="8 light0000" x="362" y="1479" width="148" height="203" frameWidth="158" frameHeight="218" frameX="-5" frameY="-1"/>
    <SubTexture name="8 light0001" x="511" y="1479" width="136" height="191" frameWidth="158" frameHeight="218" frameX="-11" frameY="-7"/>
    <SubTexture name="8 light0002" x="648" y="1479" width="126" height="179" frameWidth="158" frameHeight="218" frameX="-16" frameY="-14"/>
    <SubTexture name="8 light0003" x="775" y="1479" width="127" height="180" frameWidth="158" frameHeight="218" frameX="-16" frameY="-13"/>
    <SubTexture name="8 light0004" x="903" y="1479" width="130" height="183" frameWidth="158" frameHeight="218" frameX="-14" frameY="-11"/>
    <SubTexture name="8 light0005" x="1034" y="1479" width="132" height="186" frameWidth="158" frameHeight="218" frameX="-13" frameY="-9"/>
    <SubTexture name="8 light0006" x="1167" y="1479" width="134" height="189" frameWidth="158" frameHeight="218" frameX="-12" frameY="-8"/>
    <SubTexture name="8 light0007" x="1302" y="1479" width="138" height="191" frameWidth="158" frameHeight="218" frameX="-10" frameY="-7"/>
    <SubTexture name="8 light0008" x="1441" y="1479" width="140" height="193" frameWidth="158" frameHeight="218" frameX="-9" frameY="-6"/>
    <SubTexture name="8 light0009" x="1582" y="1479" width="142" height="196" frameWidth="158" frameHeight="218" frameX="-8" frameY="-4"/>
    <SubTexture name="8 light0010" x="1725" y="1479" width="142" height="196" frameWidth="158" frameHeight="218" frameX="-8" frameY="-4"/>
    <SubTexture name="8 light0011" x="0" y="1692" width="125" height="179" frameWidth="158" frameHeight="218" frameX="-16" frameY="-14"/>
    <SubTexture name="8 light0012" x="126" y="1692" width="125" height="179" frameWidth="158" frameHeight="218" frameX="-16" frameY="-14"/>
    <SubTexture name="8 light0013" x="126" y="1692" width="125" height="179" frameWidth="158" frameHeight="218" frameX="-16" frameY="-14"/>
    <SubTexture name="8 light0014" x="126" y="1692" width="125" height="179" frameWidth="158" frameHeight="218" frameX="-16" frameY="-14"/>
    <SubTexture name="8 light0015" x="0" y="1692" width="125" height="179" frameWidth="158" frameHeight="218" frameX="-16" frameY="-14"/>
    <SubTexture name="9 light0000" x="252" y="1692" width="146" height="201" frameWidth="163" frameHeight="218" frameX="-9" frameY="-3"/>
    <SubTexture name="9 light0001" x="399" y="1692" width="134" height="189" frameWidth="163" frameHeight="218" frameX="-15" frameY="-9"/>
    <SubTexture name="9 light0002" x="534" y="1692" width="128" height="178" frameWidth="163" frameHeight="218" frameX="-16" frameY="-15"/>
    <SubTexture name="9 light0003" x="663" y="1692" width="128" height="179" frameWidth="163" frameHeight="218" frameX="-16" frameY="-14"/>
    <SubTexture name="9 light0004" x="792" y="1692" width="130" height="183" frameWidth="163" frameHeight="218" frameX="-16" frameY="-12"/>
    <SubTexture name="9 light0005" x="923" y="1692" width="131" height="185" frameWidth="163" frameHeight="218" frameX="-16" frameY="-11"/>
    <SubTexture name="9 light0006" x="1055" y="1692" width="133" height="187" frameWidth="163" frameHeight="218" frameX="-15" frameY="-10"/>
    <SubTexture name="9 light0007" x="1189" y="1692" width="135" height="189" frameWidth="163" frameHeight="218" frameX="-15" frameY="-9"/>
    <SubTexture name="9 light0008" x="1325" y="1692" width="137" height="191" frameWidth="163" frameHeight="218" frameX="-14" frameY="-8"/>
    <SubTexture name="9 light0009" x="1463" y="1692" width="139" height="193" frameWidth="163" frameHeight="218" frameX="-13" frameY="-7"/>
    <SubTexture name="9 light0010" x="1603" y="1692" width="140" height="195" frameWidth="163" frameHeight="218" frameX="-12" frameY="-6"/>
    <SubTexture name="9 light0011" x="1744" y="1692" width="127" height="177" frameWidth="163" frameHeight="218" frameX="-16" frameY="-16"/>
    <SubTexture name="9 light0012" x="1744" y="1692" width="127" height="177" frameWidth="163" frameHeight="218" frameX="-16" frameY="-16"/>
    <SubTexture name="9 light0013" x="1744" y="1692" width="127" height="177" frameWidth="163" frameHeight="218" frameX="-16" frameY="-16"/>
    <SubTexture name="9 light0014" x="1744" y="1692" width="127" height="177" frameWidth="163" frameHeight="218" frameX="-16" frameY="-16"/>
    <SubTexture name="9 light0015" x="1744" y="1692" width="127" height="177" frameWidth="163" frameHeight="218" frameX="-16" frameY="-16"/>
</TextureAtlas>